AllMyVariousFunctions-19.10.17.1.dist-info/DESCRIPTION.rst
AllMyVariousFunctions-19.10.17.1.dist-info/METADATA
AllMyVariousFunctions-19.10.17.1.dist-info/RECORD
AllMyVariousFunctions-19.10.17.1.dist-info/WHEEL
AllMyVariousFunctions-19.10.17.1.dist-info/metadata.json
AllMyVariousFunctions-19.10.17.1.dist-info/top_level.txt
AllMyvariousFunctions/__init__.py
AllMyvariousFunctions/mutables.py
AllMyvariousFunctions/perm.py
