Metadata-Version: 2.0
Name: AllMyVariousFunctions
Version: 19.10.17.1
Summary: A module for all my various functions
Home-page: https://github.com/the42ndturtle/AllMyVariousFunctions
Author: the42ndturtle
Author-email: throwawayemail@gmail.com
License: UNKNOWN
Download-URL: https://github.com/the42ndturtle/AllMyVariousFunctions/archive/0.2.tar.gz
Keywords: my,various,functions
Platform: UNKNOWN
